listcrypt/__init__.py
listcrypt/listcrypt.py
listcrypt-1.0.1.dist-info/LICENSE
listcrypt-1.0.1.dist-info/METADATA
listcrypt-1.0.1.dist-info/WHEEL
listcrypt-1.0.1.dist-info/top_level.txt
listcrypt-1.0.1.dist-info/RECORD
