Metadata-Version: 2.1
Name: listcrypt
Version: 1.0.1
Summary: Symmetric cryptography module
Home-page: https://github.com/JustScott/ListCrypt
Author: JustScott
Author-email: <justscottmail@protonmail.com>
License: MIT
Project-URL: Bug Reports, https://github.com/JustScott/ListCrypt/issues
Keywords: python,encryption,decryption,cryptography
Classifier: Development Status :: 3 - Alpha
Classifier: Environment :: Console
Classifier: Intended Audience :: Developers
Classifier: License :: OSI Approved :: MIT License
Classifier: Operating System :: OS Independent
Classifier: Programming Language :: Python :: 3.0
Classifier: Topic :: Security :: Cryptography
License-File: LICENSE
